LICENSE
MANIFEST.in
README.rst
setup.py
pwgen_passphrase/__init__.py
pwgen_passphrase/__main__.py
pwgen_passphrase.egg-info/PKG-INFO
pwgen_passphrase.egg-info/SOURCES.txt
pwgen_passphrase.egg-info/dependency_links.txt
pwgen_passphrase.egg-info/entry_points.txt
pwgen_passphrase.egg-info/top_level.txt
pwgen_passphrase/wordlists/aspell-cs.txt.xz
pwgen_passphrase/wordlists/aspell-en.txt.xz
pwgen_passphrase/wordlists/bip0039.txt.xz
pwgen_passphrase/wordlists/cracklib-small.txt.xz
pwgen_passphrase/wordlists/diceware.txt.xz
pwgen_passphrase/wordlists/eff-long.txt.xz
pwgen_passphrase/wordlists/eff-short.txt.xz
pwgen_passphrase/wordlists/eff-short2.txt.xz
pwgen_passphrase/wordlists/skey.txt.xz