Metadata-Version: 1.1
Name: pwgen-passphrase
Version: 1.2
Summary: Secure wordlist-based passphrase generator
Home-page: https://github.com/xmikos/pwgen-passphrase
Author: Michal Krenek (Mikos)
Author-email: m.krenek@gmail.com
License: GNU GPLv3
Platform: UNKNOWN
Classifier: Development Status :: 5 - Production/Stable
Classifier: Environment :: Console
Classifier: Intended Audience :: End Users/Desktop
Classifier: Intended Audience :: System Administrators
Classifier: License :: OSI Approved :: GNU General Public License v3 or later (GPLv3+)
Classifier: Natural Language :: English
Classifier: Operating System :: OS Independent
Classifier: Programming Language :: Python :: 3
Classifier: Topic :: Security
Classifier: Topic :: Utilities
